pycefr/ClassIterTree.py
pycefr/__init__.py
pycefr/configuration.cfg
pycefr/data.csv
pycefr/data.json
pycefr/dicc.txt
pycefr/dict.py
pycefr/getcsv.py
pycefr/getjson.py
pycefr/levels.py
pycefr/pycerfl.py
pycefr-0.0.2.dist-info/LICENSE
pycefr-0.0.2.dist-info/WHEEL
pycefr-0.0.2.dist-info/METADATA
pycefr-0.0.2.dist-info/RECORD
