Metadata-Version: 2.1
Name: pycefr
Version: 0.0.2
Summary: Python Package Template
Author-email: "Raula G. Kula" <raula-k@is.naist.jp>
Classifier: License :: OSI Approved :: MIT License
Project-URL: Home, https://raux.github.io/
